skunkworks/CODEBASE
skunkworks/__init__.py
skunkworks/activate.py
skunkworks-0.0.5.dist-info/DESCRIPTION.rst
skunkworks-0.0.5.dist-info/METADATA
skunkworks-0.0.5.dist-info/RECORD
skunkworks-0.0.5.dist-info/WHEEL
skunkworks-0.0.5.dist-info/entry_points.txt
skunkworks-0.0.5.dist-info/metadata.json
skunkworks-0.0.5.dist-info/top_level.txt
