Metadata-Version: 2.0
Name: skunkworks
Version: 0.0.5
Summary: Nothing to see here.
Home-page: https://github.com/draperjames/skunkworks
Author: James Draper
Author-email: james.draper@duke.edu
License: MIT
Keywords: pandas
Platform: UNKNOWN
Classifier: Development Status :: 3 - Alpha
Classifier: Intended Audience :: Developers
Classifier: Topic :: Software Development :: Build Tools
Classifier: License :: OSI Approved :: MIT License
Classifier: Programming Language :: Python :: 3.4
Classifier: Programming Language :: Python :: 3.5
Requires-Dist: dominate
Requires-Dist: matplotlib-venn
Requires-Dist: num2words
Requires-Dist: simple-crypt
